LICENSE
MANIFEST.in
README.rst
bench-mpi.c
internal-parallel.h
internal.h
libmpi.pxd
main-mpi.c
main.c
mp-mpiu.c
mp-mpiu.h
mpsort-mpi.c
mpsort-omp.c
mpsort.h
parallel_sort.c
pyproject.toml
radixsort.c
setup.py
test-issue7.c
mpsort/__init__.py
mpsort/binding.c
mpsort/binding.pyx
mpsort/version.py
mpsort.egg-info/PKG-INFO
mpsort.egg-info/SOURCES.txt
mpsort.egg-info/dependency_links.txt
mpsort.egg-info/not-zip-safe
mpsort.egg-info/requires.txt
mpsort.egg-info/top_level.txt
mpsort/tests/__init__.py
mpsort/tests/test_mpsort.py
stdlib/msort.c
stdlib/qsort.c