Metadata-Version: 2.4
Name: mpsort
Version: 0.1.19
Summary: python binding of MP-sort, a peta scale sorting routine
Home-page: http://github.com/rainwoodman/mpsort
Author: Yu Feng
Author-email: rainwoodman@gmail.com
License: BSD-2-Clause
License-File: LICENSE
Requires-Dist: cython
Requires-Dist: numpy
Requires-Dist: mpi4py
Dynamic: author
Dynamic: author-email
Dynamic: home-page
Dynamic: license
Dynamic: license-file
Dynamic: requires-dist
Dynamic: summary
